{
  "compatibility_date": "2025-04-01",
  "main": "src/index.ts",
  "name": "openauth-template",
  "upload_source_maps": true,
  "kv_namespaces": [
    {
      "binding": "AUTH_STORAGE",
      "id": "bdb1bd4de2eb437288847ddddbed8f33"
    }
  ],
  "d1_databases": [
    {
      "binding": "AUTH_DB",
      "database_name": "openauth-template",
      "database_id": "f9ee4464-b13b-4d57-a75d-cbe8567927b8"
    }
  ],
  "observability": {
    "enabled": true
  },
  "compatibility_flags": ["nodejs_compat"]
}
